nr/io/lexer/__init__.py
nr/io/lexer/_scanner.py
nr/io/lexer/_tokenizer/extractor.py
nr/io/lexer/_tokenizer/ruleset.py
nr/io/lexer/_tokenizer/tokenizer.py
nr/io/lexer/py.typed
nr/io/lexer/rules.py
nr_io_lexer-1.0.0.dist-info/LICENSE
nr_io_lexer-1.0.0.dist-info/METADATA
nr_io_lexer-1.0.0.dist-info/WHEEL
nr_io_lexer-1.0.0.dist-info/RECORD
